fastapi_discord/__init__.py
fastapi_discord/client.py
fastapi_discord/config.py
fastapi_discord/exceptions.py
fastapi_discord/models/__init__.py
fastapi_discord/models/guild.py
fastapi_discord/models/role.py
fastapi_discord/models/user.py
fastapi_discord-0.2.7.dist-info/LICENSE
fastapi_discord-0.2.7.dist-info/METADATA
fastapi_discord-0.2.7.dist-info/WHEEL
fastapi_discord-0.2.7.dist-info/top_level.txt
fastapi_discord-0.2.7.dist-info/RECORD
