Metadata-Version: 2.1
Name: fastapi-discord
Version: 0.2.7
Summary: Discord OAuth FastAPI extension for APIs
Home-page: https://github.com/Tert0/fastapi-discord
Author: Tert0
License: MIT
Platform: UNKNOWN
Requires-Python: >=3.5
License-File: LICENSE
Requires-Dist: aiocache (==0.12.3)
Requires-Dist: aiohttp (==3.11.4)
Requires-Dist: fastapi (==0.115.5)
